dlangtools/__init__.py
dlangtools/lex.py
dlangtools/parsing.py
dlangtools-0.0.2.dist-info/LICENSE
dlangtools-0.0.2.dist-info/METADATA
dlangtools-0.0.2.dist-info/WHEEL
dlangtools-0.0.2.dist-info/top_level.txt
dlangtools-0.0.2.dist-info/RECORD
