Metadata-Version: 2.1
Name: dlangtools
Version: 0.0.2
Summary: This module will help you write simple tokenizers and parsers for your toy languages.
Author-email: Alimbekov Damir <damir.alimbekov.2002@gmail.com>
Project-URL: Homepage, https://github.com/Damiryh/dlangtools
Classifier: Programming Language :: Python :: 3
Classifier: License :: OSI Approved :: MIT License
Classifier: Operating System :: OS Independent
Requires-Python: >=3.6
License-File: LICENSE
